[
  {
    "titleText": "Top stories in 90 seconds",
    "category": "Video News",
    "subCategory": null,
    "runningTime": 85,
    "updateTime": "2025-12-03T16:31:10.965Z",
    "onClick": {
      "targetAppId": "com.dw.app.dwforsmarttv",
      "contentId": "v=49496622&list=NEWS_VIDEO:12",
      "type": "video",
      "id": 49496622,
      "launchParam": null
    },
    "providerLogo": {
      "url": "https://dwapps.de/feed/dw_white_800.png",
      "width": 800,
      "height": 800,
      "bgColor": ""
    },
    "image": {
      "url": "https://static.dw.com/image/74993855_6.jpg",
      "width": 940,
      "height": 529,
      "bgColor": ""
    },
    "image4k": {
      "url": "https://static.dw.com/image/74993855_7.jpg",
      "width": 3997,
      "height": 2250,
      "bgColor": ""
    },
    "language": "en"
  },
  {
    "titleText": "Global South drives green energy transition",
    "category": "Climate",
    "subCategory": "Politics",
    "runningTime": 420,
    "updateTime": "2025-12-02T12:05:35.906Z",
    "onClick": {
      "targetAppId": "com.dw.app.dwforsmarttv",
      "contentId": "v=74946561&list=PROFILE_TOPIC_VIDEO:4",
      "type": "video",
      "id": 74946561,
      "launchParam": null
    },
    "providerLogo": {
      "url": "https://dwapps.de/feed/dw_white_800.png",
      "width": 800,
      "height": 800,
      "bgColor": ""
    },
    "image": {
      "url": "https://static.dw.com/image/74988438_6.jpg",
      "width": 940,
      "height": 529,
      "bgColor": ""
    },
    "image4k": {
      "url": "https://static.dw.com/image/74988438_7.jpg",
      "width": 3997,
      "height": 2250,
      "bgColor": ""
    },
    "language": "en"
  },
  {
    "titleText": "Venezuelan migrants in Colombia brace as US pressure grows",
    "category": "Migration",
    "subCategory": "Conflicts",
    "runningTime": 138,
    "updateTime": "2025-11-30T20:54:32.047Z",
    "onClick": {
      "targetAppId": "com.dw.app.dwforsmarttv",
      "contentId": "v=74960414&list=GLOBAL_TOPIC_VIDEO:3",
      "type": "video",
      "id": 74960414,
      "launchParam": null
    },
    "providerLogo": {
      "url": "https://dwapps.de/feed/dw_white_800.png",
      "width": 800,
      "height": 800,
      "bgColor": ""
    },
    "image": {
      "url": "https://static.dw.com/image/74960352_6.jpg",
      "width": 940,
      "height": 529,
      "bgColor": ""
    },
    "image4k": {
      "url": "https://static.dw.com/image/74960352_7.jpg",
      "width": 3997,
      "height": 2250,
      "bgColor": ""
    },
    "language": "en"
  },
  {
    "titleText": "Peru closes southern border with Chile",
    "category": "Migration",
    "subCategory": null,
    "runningTime": 136,
    "updateTime": "2025-11-30T10:57:50.652Z",
    "onClick": {
      "targetAppId": "com.dw.app.dwforsmarttv",
      "contentId": "v=74956771&list=GLOBAL_TOPIC_VIDEO:3",
      "type": "video",
      "id": 74956771,
      "launchParam": null
    },
    "providerLogo": {
      "url": "https://dwapps.de/feed/dw_white_800.png",
      "width": 800,
      "height": 800,
      "bgColor": ""
    },
    "image": {
      "url": "https://static.dw.com/image/74956656_6.jpg",
      "width": 940,
      "height": 529,
      "bgColor": ""
    },
    "image4k": {
      "url": "https://static.dw.com/image/74956656_7.jpg",
      "width": 3997,
      "height": 2250,
      "bgColor": ""
    },
    "language": "en"
  },
  {
    "titleText": "Cigarettes: Addiction, power and propaganda",
    "category": "Society",
    "subCategory": "Politics",
    "runningTime": 520,
    "updateTime": "2025-11-30T03:17:20.079Z",
    "onClick": {
      "targetAppId": "com.dw.app.dwforsmarttv",
      "contentId": "v=74946470&list=PROFILE_TOPIC_VIDEO:1",
      "type": "video",
      "id": 74946470,
      "launchParam": null
    },
    "providerLogo": {
      "url": "https://dwapps.de/feed/dw_white_800.png",
      "width": 800,
      "height": 800,
      "bgColor": ""
    },
    "image": {
      "url": "https://static.dw.com/image/66398775_6.jpg",
      "width": 940,
      "height": 529,
      "bgColor": ""
    },
    "image4k": {
      "url": "https://static.dw.com/image/66398775_7.jpg",
      "width": 3997,
      "height": 2250,
      "bgColor": ""
    },
    "language": "en"
  },
  {
    "titleText": "US military threat fuels fear and uncertainty in Venezuela",
    "category": "Conflicts",
    "subCategory": null,
    "runningTime": 127,
    "updateTime": "2025-11-29T19:08:11.503Z",
    "onClick": {
      "targetAppId": "com.dw.app.dwforsmarttv",
      "contentId": "v=74953572&list=REGION_VIDEO:5",
      "type": "video",
      "id": 74953572,
      "launchParam": null
    },
    "providerLogo": {
      "url": "https://dwapps.de/feed/dw_white_800.png",
      "width": 800,
      "height": 800,
      "bgColor": ""
    },
    "image": {
      "url": "https://static.dw.com/image/74954110_6.jpg",
      "width": 940,
      "height": 529,
      "bgColor": ""
    },
    "image4k": {
      "url": "https://static.dw.com/image/74954110_7.jpg",
      "width": 3997,
      "height": 2250,
      "bgColor": ""
    },
    "language": "en"
  },
  {
    "titleText": "Diplomatic drive aims to end Ukraine war",
    "category": "Conflicts",
    "subCategory": null,
    "runningTime": 208,
    "updateTime": "2025-11-27T21:54:04.97Z",
    "onClick": {
      "targetAppId": "com.dw.app.dwforsmarttv",
      "contentId": "v=74932590&list=GLOBAL_TOPIC_VIDEO:2",
      "type": "video",
      "id": 74932590,
      "launchParam": null
    },
    "providerLogo": {
      "url": "https://dwapps.de/feed/dw_white_800.png",
      "width": 800,
      "height": 800,
      "bgColor": ""
    },
    "image": {
      "url": "https://static.dw.com/image/74887886_6.jpg",
      "width": 940,
      "height": 529,
      "bgColor": ""
    },
    "image4k": {
      "url": "https://static.dw.com/image/74887886_7.jpg",
      "width": 3997,
      "height": 2250,
      "bgColor": ""
    },
    "language": "en"
  },
  {
    "titleText": "Attack on National Guard soldiers 'act of terror'",
    "category": "Politics",
    "subCategory": null,
    "runningTime": 87,
    "updateTime": "2025-11-27T11:21:01.907Z",
    "onClick": {
      "targetAppId": "com.dw.app.dwforsmarttv",
      "contentId": "v=74921450&list=REGION_VIDEO:5",
      "type": "video",
      "id": 74921450,
      "launchParam": null
    },
    "providerLogo": {
      "url": "https://dwapps.de/feed/dw_white_800.png",
      "width": 800,
      "height": 800,
      "bgColor": ""
    },
    "image": {
      "url": "https://static.dw.com/image/74915936_6.jpg",
      "width": 940,
      "height": 529,
      "bgColor": ""
    },
    "image4k": {
      "url": "https://static.dw.com/image/74915936_7.jpg",
      "width": 3997,
      "height": 2250,
      "bgColor": ""
    },
    "language": "en"
  },
  {
    "titleText": "Trump downplays Witkoff leak as Ukraine peace talks progress",
    "category": "Conflicts",
    "subCategory": null,
    "runningTime": 143,
    "updateTime": "2025-11-26T18:02:23.867Z",
    "onClick": {
      "targetAppId": "com.dw.app.dwforsmarttv",
      "contentId": "v=74912904&list=GLOBAL_TOPIC_VIDEO:2",
      "type": "video",
      "id": 74912904,
      "launchParam": null
    },
    "providerLogo": {
      "url": "https://dwapps.de/feed/dw_white_800.png",
      "width": 800,
      "height": 800,
      "bgColor": ""
    },
    "image": {
      "url": "https://static.dw.com/image/74148110_6.jpg",
      "width": 940,
      "height": 529,
      "bgColor": ""
    },
    "image4k": {
      "url": "https://static.dw.com/image/74148110_7.jpg",
      "width": 3997,
      "height": 2250,
      "bgColor": ""
    },
    "language": "en"
  },
  {
    "titleText": "US military buildup off Venezuela heightens tensions",
    "category": "Conflicts",
    "subCategory": null,
    "runningTime": 232,
    "updateTime": "2025-11-24T12:41:58.687Z",
    "onClick": {
      "targetAppId": "com.dw.app.dwforsmarttv",
      "contentId": "v=74866362&list=REGION_VIDEO:6",
      "type": "video",
      "id": 74866362,
      "launchParam": null
    },
    "providerLogo": {
      "url": "https://dwapps.de/feed/dw_white_800.png",
      "width": 800,
      "height": 800,
      "bgColor": ""
    },
    "image": {
      "url": "https://static.dw.com/image/74504155_6.jpg",
      "width": 940,
      "height": 529,
      "bgColor": ""
    },
    "image4k": {
      "url": "https://static.dw.com/image/74504155_7.jpg",
      "width": 3997,
      "height": 2250,
      "bgColor": ""
    },
    "language": "en"
  },
  {
    "titleText": "Brazil's ex-president Bolsonaro taken into custody",
    "category": "Politics",
    "subCategory": null,
    "runningTime": 148,
    "updateTime": "2025-11-23T19:24:25.251Z",
    "onClick": {
      "targetAppId": "com.dw.app.dwforsmarttv",
      "contentId": "v=74855189&list=REGION_VIDEO:6",
      "type": "video",
      "id": 74855189,
      "launchParam": null
    },
    "providerLogo": {
      "url": "https://dwapps.de/feed/dw_white_800.png",
      "width": 800,
      "height": 800,
      "bgColor": ""
    },
    "image": {
      "url": "https://static.dw.com/image/74849072_6.jpg",
      "width": 940,
      "height": 529,
      "bgColor": ""
    },
    "image4k": {
      "url": "https://static.dw.com/image/74849072_7.jpg",
      "width": 3997,
      "height": 2250,
      "bgColor": ""
    },
    "language": "en"
  },
  {
    "titleText": "Ukraine's allies push back on US peace plan",
    "category": "Conflicts",
    "subCategory": "Politics",
    "runningTime": 133,
    "updateTime": "2025-11-22T18:33:41.398Z",
    "onClick": {
      "targetAppId": "com.dw.app.dwforsmarttv",
      "contentId": "v=74849878&list=GLOBAL_TOPIC_VIDEO:2",
      "type": "video",
      "id": 74849878,
      "launchParam": null
    },
    "providerLogo": {
      "url": "https://dwapps.de/feed/dw_white_800.png",
      "width": 800,
      "height": 800,
      "bgColor": ""
    },
    "image": {
      "url": "https://static.dw.com/image/74849777_6.jpg",
      "width": 940,
      "height": 529,
      "bgColor": ""
    },
    "image4k": {
      "url": "https://static.dw.com/image/74849777_7.jpg",
      "width": 3997,
      "height": 2250,
      "bgColor": ""
    },
    "language": "en"
  },
  {
    "titleText": "Trump, NYC mayor-elect Mamdani hold cordial first meeting",
    "category": "Politics",
    "subCategory": null,
    "runningTime": 118,
    "updateTime": "2025-11-22T14:01:02.151Z",
    "onClick": {
      "targetAppId": "com.dw.app.dwforsmarttv",
      "contentId": "v=74848088&list=REGION_VIDEO:5",
      "type": "video",
      "id": 74848088,
      "launchParam": null
    },
    "providerLogo": {
      "url": "https://dwapps.de/feed/dw_white_800.png",
      "width": 800,
      "height": 800,
      "bgColor": ""
    },
    "image": {
      "url": "https://static.dw.com/image/74845306_6.jpg",
      "width": 940,
      "height": 529,
      "bgColor": ""
    },
    "image4k": {
      "url": "https://static.dw.com/image/74845306_7.jpg",
      "width": 3997,
      "height": 2250,
      "bgColor": ""
    },
    "language": "en"
  },
  {
    "titleText": "US immigration raids target Democratic-run Charlotte",
    "category": "Migration",
    "subCategory": "Politics",
    "runningTime": 257,
    "updateTime": "2025-11-21T15:50:19.415Z",
    "onClick": {
      "targetAppId": "com.dw.app.dwforsmarttv",
      "contentId": "v=74841669&list=GLOBAL_TOPIC_VIDEO:3",
      "type": "video",
      "id": 74841669,
      "launchParam": null
    },
    "providerLogo": {
      "url": "https://dwapps.de/feed/dw_white_800.png",
      "width": 800,
      "height": 800,
      "bgColor": ""
    },
    "image": {
      "url": "https://static.dw.com/image/74840441_6.jpg",
      "width": 940,
      "height": 529,
      "bgColor": ""
    },
    "image4k": {
      "url": "https://static.dw.com/image/74840441_7.jpg",
      "width": 3997,
      "height": 2250,
      "bgColor": ""
    },
    "language": "en"
  },
  {
    "titleText": "COP30 climate summit enters final day in Belem, Brazil",
    "category": "Nature and Environment",
    "subCategory": "Politics",
    "runningTime": 103,
    "updateTime": "2025-11-21T08:06:43.179Z",
    "onClick": {
      "targetAppId": "com.dw.app.dwforsmarttv",
      "contentId": "v=74829695&list=REGION_VIDEO:6",
      "type": "video",
      "id": 74829695,
      "launchParam": null
    },
    "providerLogo": {
      "url": "https://dwapps.de/feed/dw_white_800.png",
      "width": 800,
      "height": 800,
      "bgColor": ""
    },
    "image": {
      "url": "https://static.dw.com/image/74827838_6.jpg",
      "width": 940,
      "height": 529,
      "bgColor": ""
    },
    "image4k": {
      "url": "https://static.dw.com/image/74827838_7.jpg",
      "width": 3997,
      "height": 2250,
      "bgColor": ""
    },
    "language": "en"
  },
  {
    "titleText": "How drones could help reforest the world's green lungs",
    "category": "Nature and Environment",
    "subCategory": "Technology",
    "runningTime": 183,
    "updateTime": "2025-11-20T16:58:39.095Z",
    "onClick": {
      "targetAppId": "com.dw.app.dwforsmarttv",
      "contentId": "v=74826012&list=REGION_VIDEO:6",
      "type": "video",
      "id": 74826012,
      "launchParam": null
    },
    "providerLogo": {
      "url": "https://dwapps.de/feed/dw_white_800.png",
      "width": 800,
      "height": 800,
      "bgColor": ""
    },
    "image": {
      "url": "https://static.dw.com/image/74825447_6.jpg",
      "width": 940,
      "height": 529,
      "bgColor": ""
    },
    "image4k": {
      "url": "https://static.dw.com/image/74825447_7.jpg",
      "width": 3997,
      "height": 2250,
      "bgColor": ""
    },
    "language": "en"
  },
  {
    "titleText": "How Belize chocolate supports rainforest conservation",
    "category": "Nature and Environment",
    "subCategory": null,
    "runningTime": 407,
    "updateTime": "2025-11-20T10:08:21.68Z",
    "onClick": {
      "targetAppId": "com.dw.app.dwforsmarttv",
      "contentId": "v=74752490&list=REGION_VIDEO:6",
      "type": "video",
      "id": 74752490,
      "launchParam": null
    },
    "providerLogo": {
      "url": "https://dwapps.de/feed/dw_white_800.png",
      "width": 800,
      "height": 800,
      "bgColor": ""
    },
    "image": {
      "url": "https://static.dw.com/image/74780938_6.jpg",
      "width": 940,
      "height": 529,
      "bgColor": ""
    },
    "image4k": {
      "url": "https://static.dw.com/image/74780938_7.jpg",
      "width": 3997,
      "height": 2250,
      "bgColor": ""
    },
    "language": "en"
  },
  {
    "titleText": "US revives Puerto Rico naval base amid Venezuela tensions",
    "category": "Conflicts",
    "subCategory": null,
    "runningTime": 155,
    "updateTime": "2025-11-19T17:00:32.764Z",
    "onClick": {
      "targetAppId": "com.dw.app.dwforsmarttv",
      "contentId": "v=74800797&list=REGION_VIDEO:5",
      "type": "video",
      "id": 74800797,
      "launchParam": null
    },
    "providerLogo": {
      "url": "https://dwapps.de/feed/dw_white_800.png",
      "width": 800,
      "height": 800,
      "bgColor": ""
    },
    "image": {
      "url": "https://static.dw.com/image/74224820_6.jpg",
      "width": 940,
      "height": 529,
      "bgColor": ""
    },
    "image4k": {
      "url": "https://static.dw.com/image/74224820_7.jpg",
      "width": 3997,
      "height": 2250,
      "bgColor": ""
    },
    "language": "en"
  },
  {
    "titleText": "What are the Epstein files? ",
    "category": "Crime",
    "subCategory": "Politics",
    "runningTime": 113,
    "updateTime": "2025-11-18T17:17:13.666Z",
    "onClick": {
      "targetAppId": "com.dw.app.dwforsmarttv",
      "contentId": "v=74793876&list=REGION_VIDEO:5",
      "type": "video",
      "id": 74793876,
      "launchParam": null
    },
    "providerLogo": {
      "url": "https://dwapps.de/feed/dw_white_800.png",
      "width": 800,
      "height": 800,
      "bgColor": ""
    },
    "image": {
      "url": "https://static.dw.com/image/60842913_6.jpg",
      "width": 940,
      "height": 529,
      "bgColor": ""
    },
    "image4k": {
      "url": "https://static.dw.com/image/60842913_7.jpg",
      "width": 3997,
      "height": 2250,
      "bgColor": ""
    },
    "language": "en"
  },
  {
    "titleText": "Lax waste controls behind Indonesian shrimp export crisis",
    "category": "Business",
    "subCategory": null,
    "runningTime": 194,
    "updateTime": "2025-11-17T10:37:48.793Z",
    "onClick": {
      "targetAppId": "com.dw.app.dwforsmarttv",
      "contentId": "v=74750831&list=REGION_VIDEO:4",
      "type": "video",
      "id": 74750831,
      "launchParam": null
    },
    "providerLogo": {
      "url": "https://dwapps.de/feed/dw_white_800.png",
      "width": 800,
      "height": 800,
      "bgColor": ""
    },
    "image": {
      "url": "https://static.dw.com/image/74467114_6.jpg",
      "width": 940,
      "height": 529,
      "bgColor": ""
    },
    "image4k": {
      "url": "https://static.dw.com/image/74467114_7.jpg",
      "width": 3997,
      "height": 2250,
      "bgColor": ""
    },
    "language": "en"
  },
  {
    "titleText": "Chile leftists advance to December's presidential runoff",
    "category": "Politics",
    "subCategory": null,
    "runningTime": 130,
    "updateTime": "2025-11-17T06:56:35.893Z",
    "onClick": {
      "targetAppId": "com.dw.app.dwforsmarttv",
      "contentId": "v=74771533&list=REGION_VIDEO:6",
      "type": "video",
      "id": 74771533,
      "launchParam": null
    },
    "providerLogo": {
      "url": "https://dwapps.de/feed/dw_white_800.png",
      "width": 800,
      "height": 800,
      "bgColor": ""
    },
    "image": {
      "url": "https://static.dw.com/image/74771311_6.jpg",
      "width": 940,
      "height": 529,
      "bgColor": ""
    },
    "image4k": {
      "url": "https://static.dw.com/image/74771311_7.jpg",
      "width": 3997,
      "height": 2250,
      "bgColor": ""
    },
    "language": "en"
  },
  {
    "titleText": "Nicolas Maduro denounces US exercises in Trinidad and Tobago",
    "category": "Conflicts",
    "subCategory": "Politics",
    "runningTime": 149,
    "updateTime": "2025-11-17T05:50:00Z",
    "onClick": {
      "targetAppId": "com.dw.app.dwforsmarttv",
      "contentId": "v=74763642&list=REGION_VIDEO:6",
      "type": "video",
      "id": 74763642,
      "launchParam": null
    },
    "providerLogo": {
      "url": "https://dwapps.de/feed/dw_white_800.png",
      "width": 800,
      "height": 800,
      "bgColor": ""
    },
    "image": {
      "url": "https://static.dw.com/image/74763783_6.jpg",
      "width": 940,
      "height": 529,
      "bgColor": ""
    },
    "image4k": {
      "url": "https://static.dw.com/image/74763783_7.jpg",
      "width": 3997,
      "height": 2250,
      "bgColor": ""
    },
    "language": "en"
  },
  {
    "titleText": "'Stop deceiving us,' say protesters at COP30",
    "category": "Climate",
    "subCategory": "Politics",
    "runningTime": 148,
    "updateTime": "2025-11-15T17:50:00Z",
    "onClick": {
      "targetAppId": "com.dw.app.dwforsmarttv",
      "contentId": "v=74761230&list=REGION_VIDEO:6",
      "type": "video",
      "id": 74761230,
      "launchParam": null
    },
    "providerLogo": {
      "url": "https://dwapps.de/feed/dw_white_800.png",
      "width": 800,
      "height": 800,
      "bgColor": ""
    },
    "image": {
      "url": "https://static.dw.com/image/74760824_6.jpg",
      "width": 940,
      "height": 529,
      "bgColor": ""
    },
    "image4k": {
      "url": "https://static.dw.com/image/74760824_7.jpg",
      "width": 3997,
      "height": 2250,
      "bgColor": ""
    },
    "language": "en"
  },
  {
    "titleText": "Why Trump can't stop the US's green energy transition",
    "category": "Climate",
    "subCategory": "Politics",
    "runningTime": 149,
    "updateTime": "2025-11-12T20:50:26.151Z",
    "onClick": {
      "targetAppId": "com.dw.app.dwforsmarttv",
      "contentId": "v=74719347&list=REGION_VIDEO:5",
      "type": "video",
      "id": 74719347,
      "launchParam": null
    },
    "providerLogo": {
      "url": "https://dwapps.de/feed/dw_white_800.png",
      "width": 800,
      "height": 800,
      "bgColor": ""
    },
    "image": {
      "url": "https://static.dw.com/image/72532268_6.jpg",
      "width": 940,
      "height": 529,
      "bgColor": ""
    },
    "image4k": {
      "url": "https://static.dw.com/image/72532268_7.jpg",
      "width": 3997,
      "height": 2250,
      "bgColor": ""
    },
    "language": "en"
  },
  {
    "titleText": "California's Newsom takes center stage at COP30",
    "category": "Climate",
    "subCategory": null,
    "runningTime": 106,
    "updateTime": "2025-11-12T14:40:26.762Z",
    "onClick": {
      "targetAppId": "com.dw.app.dwforsmarttv",
      "contentId": "v=74716358&list=REGION_VIDEO:6",
      "type": "video",
      "id": 74716358,
      "launchParam": null
    },
    "providerLogo": {
      "url": "https://dwapps.de/feed/dw_white_800.png",
      "width": 800,
      "height": 800,
      "bgColor": ""
    },
    "image": {
      "url": "https://static.dw.com/image/74710374_6.jpg",
      "width": 940,
      "height": 529,
      "bgColor": ""
    },
    "image4k": {
      "url": "https://static.dw.com/image/74710374_7.jpg",
      "width": 3997,
      "height": 2250,
      "bgColor": ""
    },
    "language": "en"
  },
  {
    "titleText": "US-Venezuela tensions rise further amid military buildup",
    "category": "Conflicts",
    "subCategory": null,
    "runningTime": 134,
    "updateTime": "2025-11-12T11:19:28.259Z",
    "onClick": {
      "targetAppId": "com.dw.app.dwforsmarttv",
      "contentId": "v=74712731&list=REGION_VIDEO:6",
      "type": "video",
      "id": 74712731,
      "launchParam": null
    },
    "providerLogo": {
      "url": "https://dwapps.de/feed/dw_white_800.png",
      "width": 800,
      "height": 800,
      "bgColor": ""
    },
    "image": {
      "url": "https://static.dw.com/image/74581732_6.jpg",
      "width": 940,
      "height": 529,
      "bgColor": ""
    },
    "image4k": {
      "url": "https://static.dw.com/image/74581732_7.jpg",
      "width": 3997,
      "height": 2250,
      "bgColor": ""
    },
    "language": "en"
  },
  {
    "titleText": "Brazil slows deforestation, boosts oil production",
    "category": "Nature and Environment",
    "subCategory": "Business",
    "runningTime": 147,
    "updateTime": "2025-11-11T10:53:25.666Z",
    "onClick": {
      "targetAppId": "com.dw.app.dwforsmarttv",
      "contentId": "v=74696524&list=REGION_VIDEO:6",
      "type": "video",
      "id": 74696524,
      "launchParam": null
    },
    "providerLogo": {
      "url": "https://dwapps.de/feed/dw_white_800.png",
      "width": 800,
      "height": 800,
      "bgColor": ""
    },
    "image": {
      "url": "https://static.dw.com/image/74698204_6.jpg",
      "width": 940,
      "height": 529,
      "bgColor": ""
    },
    "image4k": {
      "url": "https://static.dw.com/image/74698204_7.jpg",
      "width": 3997,
      "height": 2250,
      "bgColor": ""
    },
    "language": "en"
  },
  {
    "titleText": "Senate deal to end US shutdown faces tense vote in the House",
    "category": "Politics",
    "subCategory": null,
    "runningTime": 103,
    "updateTime": "2025-11-11T07:49:35.785Z",
    "onClick": {
      "targetAppId": "com.dw.app.dwforsmarttv",
      "contentId": "v=74694667&list=REGION_VIDEO:5",
      "type": "video",
      "id": 74694667,
      "launchParam": null
    },
    "providerLogo": {
      "url": "https://dwapps.de/feed/dw_white_800.png",
      "width": 800,
      "height": 800,
      "bgColor": ""
    },
    "image": {
      "url": "https://static.dw.com/image/74682591_6.jpg",
      "width": 940,
      "height": 529,
      "bgColor": ""
    },
    "image4k": {
      "url": "https://static.dw.com/image/74682591_7.jpg",
      "width": 3997,
      "height": 2250,
      "bgColor": ""
    },
    "language": "en"
  },
  {
    "titleText": "Syria's al-Sharaa to meet Trump at the White House",
    "category": "Politics",
    "subCategory": null,
    "runningTime": 124,
    "updateTime": "2025-11-10T12:00:09.173Z",
    "onClick": {
      "targetAppId": "com.dw.app.dwforsmarttv",
      "contentId": "v=74687127&list=REGION_VIDEO:9",
      "type": "video",
      "id": 74687127,
      "launchParam": null
    },
    "providerLogo": {
      "url": "https://dwapps.de/feed/dw_white_800.png",
      "width": 800,
      "height": 800,
      "bgColor": ""
    },
    "image": {
      "url": "https://static.dw.com/image/74676942_6.jpg",
      "width": 940,
      "height": 529,
      "bgColor": ""
    },
    "image4k": {
      "url": "https://static.dw.com/image/74676942_7.jpg",
      "width": 3997,
      "height": 2250,
      "bgColor": ""
    },
    "language": "en"
  },
  {
    "titleText": "Report COP30 Brazil: Protect forests while drilling for oil?",
    "category": "Business",
    "subCategory": "Climate",
    "runningTime": 498,
    "updateTime": "2025-11-10T00:30:00Z",
    "onClick": {
      "targetAppId": "com.dw.app.dwforsmarttv",
      "contentId": "v=74668422&list=REGION_VIDEO:6",
      "type": "video",
      "id": 74668422,
      "launchParam": null
    },
    "providerLogo": {
      "url": "https://dwapps.de/feed/dw_white_800.png",
      "width": 800,
      "height": 800,
      "bgColor": ""
    },
    "image": {
      "url": "https://static.dw.com/image/74699369_6.jpg",
      "width": 940,
      "height": 529,
      "bgColor": ""
    },
    "image4k": {
      "url": "https://static.dw.com/image/74699369_7.jpg",
      "width": 3997,
      "height": 2250,
      "bgColor": ""
    },
    "language": "en"
  },
  {
    "titleText": "Donald Trump continues push for Greenland to join the US",
    "category": "Society",
    "subCategory": "Politics",
    "runningTime": 407,
    "updateTime": "2025-11-09T16:45:06.136Z",
    "onClick": {
      "targetAppId": "com.dw.app.dwforsmarttv",
      "contentId": "v=74576610&list=PROFILE_TOPIC_VIDEO:1",
      "type": "video",
      "id": 74576610,
      "launchParam": null
    },
    "providerLogo": {
      "url": "https://dwapps.de/feed/dw_white_800.png",
      "width": 800,
      "height": 800,
      "bgColor": ""
    },
    "image": {
      "url": "https://static.dw.com/image/74668381_6.jpg",
      "width": 940,
      "height": 529,
      "bgColor": ""
    },
    "image4k": {
      "url": "https://static.dw.com/image/74668381_7.jpg",
      "width": 3997,
      "height": 2250,
      "bgColor": ""
    },
    "language": "en"
  },
  {
    "titleText": "Fishers in Colombia worry as US strikes alleged drug boats",
    "category": "Crime",
    "subCategory": null,
    "runningTime": 151,
    "updateTime": "2025-11-09T09:31:19.633Z",
    "onClick": {
      "targetAppId": "com.dw.app.dwforsmarttv",
      "contentId": "v=74677415&list=REGION_VIDEO:6",
      "type": "video",
      "id": 74677415,
      "launchParam": null
    },
    "providerLogo": {
      "url": "https://dwapps.de/feed/dw_white_800.png",
      "width": 800,
      "height": 800,
      "bgColor": ""
    },
    "image": {
      "url": "https://static.dw.com/image/74677399_6.jpg",
      "width": 940,
      "height": 529,
      "bgColor": ""
    },
    "image4k": {
      "url": "https://static.dw.com/image/74677399_7.jpg",
      "width": 3997,
      "height": 2250,
      "bgColor": ""
    },
    "language": "en"
  },
  {
    "titleText": "US food banks strain under surging demand due to SNAP freeze",
    "category": "Politics",
    "subCategory": "Society",
    "runningTime": 123,
    "updateTime": "2025-11-08T21:44:41.626Z",
    "onClick": {
      "targetAppId": "com.dw.app.dwforsmarttv",
      "contentId": "v=74675461&list=REGION_VIDEO:5",
      "type": "video",
      "id": 74675461,
      "launchParam": null
    },
    "providerLogo": {
      "url": "https://dwapps.de/feed/dw_white_800.png",
      "width": 800,
      "height": 800,
      "bgColor": ""
    },
    "image": {
      "url": "https://static.dw.com/image/74581855_6.jpg",
      "width": 940,
      "height": 529,
      "bgColor": ""
    },
    "image4k": {
      "url": "https://static.dw.com/image/74581855_7.jpg",
      "width": 3997,
      "height": 2250,
      "bgColor": ""
    },
    "language": "en"
  },
  {
    "titleText": "Colombia hosts talks on US drug strikes, EU cocaine crisis",
    "category": "Crime",
    "subCategory": null,
    "runningTime": 143,
    "updateTime": "2025-11-08T19:26:43.198Z",
    "onClick": {
      "targetAppId": "com.dw.app.dwforsmarttv",
      "contentId": "v=74675213&list=REGION_VIDEO:6",
      "type": "video",
      "id": 74675213,
      "launchParam": null
    },
    "providerLogo": {
      "url": "https://dwapps.de/feed/dw_white_800.png",
      "width": 800,
      "height": 800,
      "bgColor": ""
    },
    "image": {
      "url": "https://static.dw.com/image/73135051_6.jpg",
      "width": 940,
      "height": 529,
      "bgColor": ""
    },
    "image4k": {
      "url": "https://static.dw.com/image/73135051_7.jpg",
      "width": 3997,
      "height": 2250,
      "bgColor": ""
    },
    "language": "en"
  },
  {
    "titleText": "Brazil pushes for Tropical Forests Forever Facility",
    "category": "Climate",
    "subCategory": "Politics",
    "runningTime": 118,
    "updateTime": "2025-11-08T14:35:40.948Z",
    "onClick": {
      "targetAppId": "com.dw.app.dwforsmarttv",
      "contentId": "v=74673465&list=REGION_VIDEO:6",
      "type": "video",
      "id": 74673465,
      "launchParam": null
    },
    "providerLogo": {
      "url": "https://dwapps.de/feed/dw_white_800.png",
      "width": 800,
      "height": 800,
      "bgColor": ""
    },
    "image": {
      "url": "https://static.dw.com/image/74673901_6.jpg",
      "width": 940,
      "height": 529,
      "bgColor": ""
    },
    "image4k": {
      "url": "https://static.dw.com/image/74673901_7.jpg",
      "width": 3997,
      "height": 2250,
      "bgColor": ""
    },
    "language": "en"
  },
  {
    "titleText": "What Mamdani's election means for Muslims in New York City",
    "category": "Politics",
    "subCategory": "Society",
    "runningTime": 218,
    "updateTime": "2025-11-08T10:29:41.173Z",
    "onClick": {
      "targetAppId": "com.dw.app.dwforsmarttv",
      "contentId": "v=74649693&list=PROFILE_TOPIC_VIDEO:1",
      "type": "video",
      "id": 74649693,
      "launchParam": null
    },
    "providerLogo": {
      "url": "https://dwapps.de/feed/dw_white_800.png",
      "width": 800,
      "height": 800,
      "bgColor": ""
    },
    "image": {
      "url": "https://static.dw.com/image/74621037_6.jpg",
      "width": 940,
      "height": 529,
      "bgColor": ""
    },
    "image4k": {
      "url": "https://static.dw.com/image/74621037_7.jpg",
      "width": 3997,
      "height": 2250,
      "bgColor": ""
    },
    "language": "en"
  },
  {
    "titleText": "'America' — Maurizio Cattelan's gold toilet goes on sale ",
    "category": "Arts",
    "subCategory": null,
    "runningTime": 124,
    "updateTime": "2025-11-08T09:11:17.623Z",
    "onClick": {
      "targetAppId": "com.dw.app.dwforsmarttv",
      "contentId": "v=74671532&list=REGION_VIDEO:5",
      "type": "video",
      "id": 74671532,
      "launchParam": null
    },
    "providerLogo": {
      "url": "https://dwapps.de/feed/dw_white_800.png",
      "width": 800,
      "height": 800,
      "bgColor": ""
    },
    "image": {
      "url": "https://static.dw.com/image/74671679_6.jpg",
      "width": 940,
      "height": 529,
      "bgColor": ""
    },
    "image4k": {
      "url": "https://static.dw.com/image/74671679_7.jpg",
      "width": 3997,
      "height": 2250,
      "bgColor": ""
    },
    "language": "en"
  },
  {
    "titleText": "US government shutdown leads to flight cancellations",
    "category": "Politics",
    "subCategory": null,
    "runningTime": 118,
    "updateTime": "2025-11-08T08:12:39.928Z",
    "onClick": {
      "targetAppId": "com.dw.app.dwforsmarttv",
      "contentId": "v=74671412&list=REGION_VIDEO:5",
      "type": "video",
      "id": 74671412,
      "launchParam": null
    },
    "providerLogo": {
      "url": "https://dwapps.de/feed/dw_white_800.png",
      "width": 800,
      "height": 800,
      "bgColor": ""
    },
    "image": {
      "url": "https://static.dw.com/image/74671452_6.jpg",
      "width": 940,
      "height": 529,
      "bgColor": ""
    },
    "image4k": {
      "url": "https://static.dw.com/image/74671452_7.jpg",
      "width": 3997,
      "height": 2250,
      "bgColor": ""
    },
    "language": "en"
  },
  {
    "titleText": "Colombia's CNEB armed group gives up 14 tons of arms",
    "category": "Politics",
    "subCategory": null,
    "runningTime": 159,
    "updateTime": "2025-11-07T21:40:07.731Z",
    "onClick": {
      "targetAppId": "com.dw.app.dwforsmarttv",
      "contentId": "v=74669617&list=REGION_VIDEO:6",
      "type": "video",
      "id": 74669617,
      "launchParam": null
    },
    "providerLogo": {
      "url": "https://dwapps.de/feed/dw_white_800.png",
      "width": 800,
      "height": 800,
      "bgColor": ""
    },
    "image": {
      "url": "https://static.dw.com/image/74669444_6.jpg",
      "width": 940,
      "height": 529,
      "bgColor": ""
    },
    "image4k": {
      "url": "https://static.dw.com/image/74669444_7.jpg",
      "width": 3997,
      "height": 2250,
      "bgColor": ""
    },
    "language": "en"
  },
  {
    "titleText": "Brazil's $125 billion plan to save the world's rainforests",
    "category": "Nature and Environment",
    "subCategory": "Climate",
    "runningTime": 570,
    "updateTime": "2025-11-07T17:45:33.508Z",
    "onClick": {
      "targetAppId": "com.dw.app.dwforsmarttv",
      "contentId": "v=74662937&list=GLOBAL_TOPIC_VIDEO:4",
      "type": "video",
      "id": 74662937,
      "launchParam": null
    },
    "providerLogo": {
      "url": "https://dwapps.de/feed/dw_white_800.png",
      "width": 800,
      "height": 800,
      "bgColor": ""
    },
    "image": {
      "url": "https://static.dw.com/image/69883069_6.jpg",
      "width": 940,
      "height": 529,
      "bgColor": ""
    },
    "image4k": {
      "url": "https://static.dw.com/image/69883069_7.jpg",
      "width": 3997,
      "height": 2250,
      "bgColor": ""
    },
    "language": "en"
  },
  {
    "titleText": "Merz at COP30: 'Let us seize this opportunity'",
    "category": "Politics",
    "subCategory": "Climate",
    "runningTime": 336,
    "updateTime": "2025-11-07T17:10:18.515Z",
    "onClick": {
      "targetAppId": "com.dw.app.dwforsmarttv",
      "contentId": "v=74667521&list=REGION_VIDEO:6",
      "type": "video",
      "id": 74667521,
      "launchParam": null
    },
    "providerLogo": {
      "url": "https://dwapps.de/feed/dw_white_800.png",
      "width": 800,
      "height": 800,
      "bgColor": ""
    },
    "image": {
      "url": "https://static.dw.com/image/74663744_6.jpg",
      "width": 940,
      "height": 529,
      "bgColor": ""
    },
    "image4k": {
      "url": "https://static.dw.com/image/74663744_7.jpg",
      "width": 3997,
      "height": 2250,
      "bgColor": ""
    },
    "language": "en"
  },
  {
    "titleText": "Hungary's Viktor Orban vists Donald Trump in Washington",
    "category": "Politics",
    "subCategory": null,
    "runningTime": 139,
    "updateTime": "2025-11-07T17:06:33.274Z",
    "onClick": {
      "targetAppId": "com.dw.app.dwforsmarttv",
      "contentId": "v=74667518&list=GLOBAL_TOPIC_VIDEO:6",
      "type": "video",
      "id": 74667518,
      "launchParam": null
    },
    "providerLogo": {
      "url": "https://dwapps.de/feed/dw_white_800.png",
      "width": 800,
      "height": 800,
      "bgColor": ""
    },
    "image": {
      "url": "https://static.dw.com/image/69634516_6.jpg",
      "width": 940,
      "height": 529,
      "bgColor": ""
    },
    "image4k": {
      "url": "https://static.dw.com/image/69634516_7.jpg",
      "width": 3997,
      "height": 2250,
      "bgColor": ""
    },
    "language": "en"
  },
  {
    "titleText": "Tesla approves $1 trillion pay deal for CEO Elon Musk",
    "category": "Business",
    "subCategory": "Politics",
    "runningTime": 130,
    "updateTime": "2025-11-07T14:22:38.492Z",
    "onClick": {
      "targetAppId": "com.dw.app.dwforsmarttv",
      "contentId": "v=74662869&list=REGION_VIDEO:5",
      "type": "video",
      "id": 74662869,
      "launchParam": null
    },
    "providerLogo": {
      "url": "https://dwapps.de/feed/dw_white_800.png",
      "width": 800,
      "height": 800,
      "bgColor": ""
    },
    "image": {
      "url": "https://static.dw.com/image/69888628_6.jpg",
      "width": 940,
      "height": 529,
      "bgColor": ""
    },
    "image4k": {
      "url": "https://static.dw.com/image/69888628_7.jpg",
      "width": 3997,
      "height": 2250,
      "bgColor": ""
    },
    "language": "en"
  },
  {
    "titleText": "Palantir's AI rise: How dangerous is the data giant?",
    "category": "Human Rights",
    "subCategory": null,
    "runningTime": 279,
    "updateTime": "2025-11-07T12:00:07.7Z",
    "onClick": {
      "targetAppId": "com.dw.app.dwforsmarttv",
      "contentId": "v=74660094&list=REGION_VIDEO:5",
      "type": "video",
      "id": 74660094,
      "launchParam": null
    },
    "providerLogo": {
      "url": "https://dwapps.de/feed/dw_white_800.png",
      "width": 800,
      "height": 800,
      "bgColor": ""
    },
    "image": {
      "url": "https://static.dw.com/image/73463280_6.jpg",
      "width": 940,
      "height": 529,
      "bgColor": ""
    },
    "image4k": {
      "url": "https://static.dw.com/image/73463280_7.jpg",
      "width": 3997,
      "height": 2250,
      "bgColor": ""
    },
    "language": "en"
  },
  {
    "titleText": "Hurricane Melissa's severity linked to global warming: Study",
    "category": "Climate",
    "subCategory": "Catastrophe",
    "runningTime": 136,
    "updateTime": "2025-11-07T08:33:14.154Z",
    "onClick": {
      "targetAppId": "com.dw.app.dwforsmarttv",
      "contentId": "v=74654137&list=GLOBAL_TOPIC_VIDEO:4",
      "type": "video",
      "id": 74654137,
      "launchParam": null
    },
    "providerLogo": {
      "url": "https://dwapps.de/feed/dw_white_800.png",
      "width": 800,
      "height": 800,
      "bgColor": ""
    },
    "image": {
      "url": "https://static.dw.com/image/74552577_6.jpg",
      "width": 940,
      "height": 529,
      "bgColor": ""
    },
    "image4k": {
      "url": "https://static.dw.com/image/74552577_7.jpg",
      "width": 3997,
      "height": 2250,
      "bgColor": ""
    },
    "language": "en"
  },
  {
    "titleText": "COP30 nears as pressure mounts over climate's social impacts",
    "category": "Climate",
    "subCategory": null,
    "runningTime": 165,
    "updateTime": "2025-11-06T12:17:19.718Z",
    "onClick": {
      "targetAppId": "com.dw.app.dwforsmarttv",
      "contentId": "v=74641973&list=REGION_VIDEO:6",
      "type": "video",
      "id": 74641973,
      "launchParam": null
    },
    "providerLogo": {
      "url": "https://dwapps.de/feed/dw_white_800.png",
      "width": 800,
      "height": 800,
      "bgColor": ""
    },
    "image": {
      "url": "https://static.dw.com/image/74623807_6.jpg",
      "width": 940,
      "height": 529,
      "bgColor": ""
    },
    "image4k": {
      "url": "https://static.dw.com/image/74623807_7.jpg",
      "width": 3997,
      "height": 2250,
      "bgColor": ""
    },
    "language": "en"
  },
  {
    "titleText": "US shutdown halts food aid, leaving millions in the lurch",
    "category": "Politics",
    "subCategory": "Society",
    "runningTime": 217,
    "updateTime": "2025-11-06T11:07:31.416Z",
    "onClick": {
      "targetAppId": "com.dw.app.dwforsmarttv",
      "contentId": "v=74639322&list=REGION_VIDEO:5",
      "type": "video",
      "id": 74639322,
      "launchParam": null
    },
    "providerLogo": {
      "url": "https://dwapps.de/feed/dw_white_800.png",
      "width": 800,
      "height": 800,
      "bgColor": ""
    },
    "image": {
      "url": "https://static.dw.com/image/71113223_6.jpg",
      "width": 940,
      "height": 529,
      "bgColor": ""
    },
    "image4k": {
      "url": "https://static.dw.com/image/71113223_7.jpg",
      "width": 3997,
      "height": 2250,
      "bgColor": ""
    },
    "language": "en"
  },
  {
    "titleText": "NYC Mayor-elect Mamdani to confront Trump immigration agenda",
    "category": "Politics",
    "subCategory": null,
    "runningTime": 161,
    "updateTime": "2025-11-05T12:28:25.481Z",
    "onClick": {
      "targetAppId": "com.dw.app.dwforsmarttv",
      "contentId": "v=74626704&list=REGION_VIDEO:5",
      "type": "video",
      "id": 74626704,
      "launchParam": null
    },
    "providerLogo": {
      "url": "https://dwapps.de/feed/dw_white_800.png",
      "width": 800,
      "height": 800,
      "bgColor": ""
    },
    "image": {
      "url": "https://static.dw.com/image/74621519_6.jpg",
      "width": 940,
      "height": 529,
      "bgColor": ""
    },
    "image4k": {
      "url": "https://static.dw.com/image/74621519_7.jpg",
      "width": 3997,
      "height": 2250,
      "bgColor": ""
    },
    "language": "en"
  },
  {
    "titleText": "Stranded animals rescued from abandoned zoo in Argentina",
    "category": "Nature and Environment",
    "subCategory": "Society",
    "runningTime": 154,
    "updateTime": "2025-11-02T09:20:07.708Z",
    "onClick": {
      "targetAppId": "com.dw.app.dwforsmarttv",
      "contentId": "v=74589363&list=GLOBAL_TOPIC_VIDEO:5",
      "type": "video",
      "id": 74589363,
      "launchParam": null
    },
    "providerLogo": {
      "url": "https://dwapps.de/feed/dw_white_800.png",
      "width": 800,
      "height": 800,
      "bgColor": ""
    },
    "image": {
      "url": "https://static.dw.com/image/74581442_6.jpg",
      "width": 940,
      "height": 529,
      "bgColor": ""
    },
    "image4k": {
      "url": "https://static.dw.com/image/74581442_7.jpg",
      "width": 3997,
      "height": 2250,
      "bgColor": ""
    },
    "language": "en"
  },
  {
    "titleText": "Can climate games boost environmental awareness?",
    "category": "Digital World",
    "subCategory": "Climate",
    "runningTime": 144,
    "updateTime": "2025-10-30T19:53:42.1Z",
    "onClick": {
      "targetAppId": "com.dw.app.dwforsmarttv",
      "contentId": "v=74562592&list=PROFILE_TOPIC_VIDEO:3",
      "type": "video",
      "id": 74562592,
      "launchParam": null
    },
    "providerLogo": {
      "url": "https://dwapps.de/feed/dw_white_800.png",
      "width": 800,
      "height": 800,
      "bgColor": ""
    },
    "image": {
      "url": "https://static.dw.com/image/74559818_6.jpg",
      "width": 940,
      "height": 529,
      "bgColor": ""
    },
    "image4k": {
      "url": "https://static.dw.com/image/74559818_7.jpg",
      "width": 3997,
      "height": 2250,
      "bgColor": ""
    },
    "language": "en"
  },
  {
    "titleText": "Jamaica reels as Hurricane Melissa leaves behind devastation",
    "category": "Catastrophe",
    "subCategory": "Nature and Environment",
    "runningTime": 132,
    "updateTime": "2025-10-30T18:08:01.502Z",
    "onClick": {
      "targetAppId": "com.dw.app.dwforsmarttv",
      "contentId": "v=74562118&list=GLOBAL_TOPIC_VIDEO:4",
      "type": "video",
      "id": 74562118,
      "launchParam": null
    },
    "providerLogo": {
      "url": "https://dwapps.de/feed/dw_white_800.png",
      "width": 800,
      "height": 800,
      "bgColor": ""
    },
    "image": {
      "url": "https://static.dw.com/image/74550415_6.jpg",
      "width": 940,
      "height": 529,
      "bgColor": ""
    },
    "image4k": {
      "url": "https://static.dw.com/image/74550415_7.jpg",
      "width": 3997,
      "height": 2250,
      "bgColor": ""
    },
    "language": "en"
  },
  {
    "titleText": "No end in sight for US government shutdown ",
    "category": "Politics",
    "subCategory": null,
    "runningTime": 130,
    "updateTime": "2025-10-30T10:15:25.068Z",
    "onClick": {
      "targetAppId": "com.dw.app.dwforsmarttv",
      "contentId": "v=74544829&list=REGION_VIDEO:5",
      "type": "video",
      "id": 74544829,
      "launchParam": null
    },
    "providerLogo": {
      "url": "https://dwapps.de/feed/dw_white_800.png",
      "width": 800,
      "height": 800,
      "bgColor": ""
    },
    "image": {
      "url": "https://static.dw.com/image/74545172_6.jpg",
      "width": 940,
      "height": 529,
      "bgColor": ""
    },
    "image4k": {
      "url": "https://static.dw.com/image/74545172_7.jpg",
      "width": 3997,
      "height": 2250,
      "bgColor": ""
    },
    "language": "en"
  },
  {
    "titleText": "Trump's bailout push for Milei sways Argentina's politics",
    "category": "Politics",
    "subCategory": "Business",
    "runningTime": 133,
    "updateTime": "2025-10-28T13:42:57.707Z",
    "onClick": {
      "targetAppId": "com.dw.app.dwforsmarttv",
      "contentId": "v=74527439&list=PROFILE_TOPIC_VIDEO:2",
      "type": "video",
      "id": 74527439,
      "launchParam": null
    },
    "providerLogo": {
      "url": "https://dwapps.de/feed/dw_white_800.png",
      "width": 800,
      "height": 800,
      "bgColor": ""
    },
    "image": {
      "url": "https://static.dw.com/image/67499224_6.jpg",
      "width": 940,
      "height": 529,
      "bgColor": ""
    },
    "image4k": {
      "url": "https://static.dw.com/image/67499224_7.jpg",
      "width": 3997,
      "height": 2250,
      "bgColor": ""
    },
    "language": "en"
  },
  {
    "titleText": "Democrats eye Zohran Mamdani's rise in New York mayoral race",
    "category": "Politics",
    "subCategory": null,
    "runningTime": 157,
    "updateTime": "2025-10-28T08:11:31.873Z",
    "onClick": {
      "targetAppId": "com.dw.app.dwforsmarttv",
      "contentId": "v=74520022&list=REGION_VIDEO:5",
      "type": "video",
      "id": 74520022,
      "launchParam": null
    },
    "providerLogo": {
      "url": "https://dwapps.de/feed/dw_white_800.png",
      "width": 800,
      "height": 800,
      "bgColor": ""
    },
    "image": {
      "url": "https://static.dw.com/image/74517601_6.jpg",
      "width": 940,
      "height": 529,
      "bgColor": ""
    },
    "image4k": {
      "url": "https://static.dw.com/image/74517601_7.jpg",
      "width": 3997,
      "height": 2250,
      "bgColor": ""
    },
    "language": "en"
  },
  {
    "titleText": "Jamaica braces for Category 5 Hurricane Melissa",
    "category": "Catastrophe",
    "subCategory": null,
    "runningTime": 111,
    "updateTime": "2025-10-27T18:45:10.626Z",
    "onClick": {
      "targetAppId": "com.dw.app.dwforsmarttv",
      "contentId": "v=74517834&list=GLOBAL_TOPIC_VIDEO:4",
      "type": "video",
      "id": 74517834,
      "launchParam": null
    },
    "providerLogo": {
      "url": "https://dwapps.de/feed/dw_white_800.png",
      "width": 800,
      "height": 800,
      "bgColor": ""
    },
    "image": {
      "url": "https://static.dw.com/image/74492234_6.jpg",
      "width": 940,
      "height": 529,
      "bgColor": ""
    },
    "image4k": {
      "url": "https://static.dw.com/image/74492234_7.jpg",
      "width": 3997,
      "height": 2250,
      "bgColor": ""
    },
    "language": "en"
  },
  {
    "titleText": "US imposes sanctions on Russian oil giants",
    "category": "Conflicts",
    "subCategory": "Business",
    "runningTime": 161,
    "updateTime": "2025-10-23T09:38:30.477Z",
    "onClick": {
      "targetAppId": "com.dw.app.dwforsmarttv",
      "contentId": "v=74468471&list=GLOBAL_TOPIC_VIDEO:6",
      "type": "video",
      "id": 74468471,
      "launchParam": null
    },
    "providerLogo": {
      "url": "https://dwapps.de/feed/dw_white_800.png",
      "width": 800,
      "height": 800,
      "bgColor": ""
    },
    "image": {
      "url": "https://static.dw.com/image/74074979_6.jpg",
      "width": 940,
      "height": 529,
      "bgColor": ""
    },
    "image4k": {
      "url": "https://static.dw.com/image/74074979_7.jpg",
      "width": 3997,
      "height": 2250,
      "bgColor": ""
    },
    "language": "en"
  },
  {
    "titleText": "Trump 2.0 endangers iconic US national parks",
    "category": "Business",
    "subCategory": "Nature and Environment",
    "runningTime": 399,
    "updateTime": "2025-10-23T08:54:11.199Z",
    "onClick": {
      "targetAppId": "com.dw.app.dwforsmarttv",
      "contentId": "v=74407382&list=REGION_VIDEO:5",
      "type": "video",
      "id": 74407382,
      "launchParam": null
    },
    "providerLogo": {
      "url": "https://dwapps.de/feed/dw_white_800.png",
      "width": 800,
      "height": 800,
      "bgColor": ""
    },
    "image": {
      "url": "https://static.dw.com/image/6607782_6.jpg",
      "width": 940,
      "height": 529,
      "bgColor": ""
    },
    "image4k": {
      "url": "https://static.dw.com/image/6607782_7.jpg",
      "width": 3997,
      "height": 2250,
      "bgColor": ""
    },
    "language": "en"
  },
  {
    "titleText": "Construction begins on new White House ballroom",
    "category": "Politics",
    "subCategory": null,
    "runningTime": 125,
    "updateTime": "2025-10-22T08:50:58.758Z",
    "onClick": {
      "targetAppId": "com.dw.app.dwforsmarttv",
      "contentId": "v=74452565&list=REGION_VIDEO:5",
      "type": "video",
      "id": 74452565,
      "launchParam": null
    },
    "providerLogo": {
      "url": "https://dwapps.de/feed/dw_white_800.png",
      "width": 800,
      "height": 800,
      "bgColor": ""
    },
    "image": {
      "url": "https://static.dw.com/image/74452078_6.jpg",
      "width": 940,
      "height": 529,
      "bgColor": ""
    },
    "image4k": {
      "url": "https://static.dw.com/image/74452078_7.jpg",
      "width": 3997,
      "height": 2250,
      "bgColor": ""
    },
    "language": "en"
  },
  {
    "titleText": "Millions across US join mass 'No Kings' anti-Trump protests",
    "category": "Politics",
    "subCategory": null,
    "runningTime": 139,
    "updateTime": "2025-10-18T21:52:19.728Z",
    "onClick": {
      "targetAppId": "com.dw.app.dwforsmarttv",
      "contentId": "v=74413378&list=REGION_VIDEO:5",
      "type": "video",
      "id": 74413378,
      "launchParam": null
    },
    "providerLogo": {
      "url": "https://dwapps.de/feed/dw_white_800.png",
      "width": 800,
      "height": 800,
      "bgColor": ""
    },
    "image": {
      "url": "https://static.dw.com/image/74413104_6.jpg",
      "width": 940,
      "height": 529,
      "bgColor": ""
    },
    "image4k": {
      "url": "https://static.dw.com/image/74413104_7.jpg",
      "width": 3997,
      "height": 2250,
      "bgColor": ""
    },
    "language": "en"
  },
  {
    "titleText": "Trump rejects Zelenskyy's Tomahawk request",
    "category": "Politics",
    "subCategory": null,
    "runningTime": 151,
    "updateTime": "2025-10-18T07:47:34.517Z",
    "onClick": {
      "targetAppId": "com.dw.app.dwforsmarttv",
      "contentId": "v=74408808&list=GLOBAL_TOPIC_VIDEO:6",
      "type": "video",
      "id": 74408808,
      "launchParam": null
    },
    "providerLogo": {
      "url": "https://dwapps.de/feed/dw_white_800.png",
      "width": 800,
      "height": 800,
      "bgColor": ""
    },
    "image": {
      "url": "https://static.dw.com/image/74408154_6.jpg",
      "width": 940,
      "height": 529,
      "bgColor": ""
    },
    "image4k": {
      "url": "https://static.dw.com/image/74408154_7.jpg",
      "width": 3997,
      "height": 2250,
      "bgColor": ""
    },
    "language": "en"
  },
  {
    "titleText": "Trump, Zelenskyy hold 'cordial' White House meeting",
    "category": "Conflicts",
    "subCategory": null,
    "runningTime": 295,
    "updateTime": "2025-10-17T21:06:27.835Z",
    "onClick": {
      "targetAppId": "com.dw.app.dwforsmarttv",
      "contentId": "v=74407446&list=GLOBAL_TOPIC_VIDEO:6",
      "type": "video",
      "id": 74407446,
      "launchParam": null
    },
    "providerLogo": {
      "url": "https://dwapps.de/feed/dw_white_800.png",
      "width": 800,
      "height": 800,
      "bgColor": ""
    },
    "image": {
      "url": "https://static.dw.com/image/74407074_6.jpg",
      "width": 940,
      "height": 529,
      "bgColor": ""
    },
    "image4k": {
      "url": "https://static.dw.com/image/74407074_7.jpg",
      "width": 3997,
      "height": 2250,
      "bgColor": ""
    },
    "language": "en"
  },
  {
    "titleText": "Ex-Trump adviser John Bolton charged over classified info",
    "category": "Law and Justice",
    "subCategory": "Politics",
    "runningTime": 124,
    "updateTime": "2025-10-17T07:27:23.813Z",
    "onClick": {
      "targetAppId": "com.dw.app.dwforsmarttv",
      "contentId": "v=74394356&list=REGION_VIDEO:5",
      "type": "video",
      "id": 74394356,
      "launchParam": null
    },
    "providerLogo": {
      "url": "https://dwapps.de/feed/dw_white_800.png",
      "width": 800,
      "height": 800,
      "bgColor": ""
    },
    "image": {
      "url": "https://static.dw.com/image/50407908_6.jpg",
      "width": 940,
      "height": 529,
      "bgColor": ""
    },
    "image4k": {
      "url": "https://static.dw.com/image/50407908_7.jpg",
      "width": 3997,
      "height": 2250,
      "bgColor": ""
    },
    "language": "en"
  },
  {
    "titleText": "Mexico City's 'Trump refugees' cause housing crisis",
    "category": "Society",
    "subCategory": "Business",
    "runningTime": 345,
    "updateTime": "2025-10-13T00:30:00Z",
    "onClick": {
      "targetAppId": "com.dw.app.dwforsmarttv",
      "contentId": "v=74314759&list=PROFILE_TOPIC_VIDEO:2",
      "type": "video",
      "id": 74314759,
      "launchParam": null
    },
    "providerLogo": {
      "url": "https://dwapps.de/feed/dw_white_800.png",
      "width": 800,
      "height": 800,
      "bgColor": ""
    },
    "image": {
      "url": "https://static.dw.com/image/74301643_6.jpeg",
      "width": 940,
      "height": 529,
      "bgColor": ""
    },
    "image4k": {
      "url": "https://static.dw.com/image/74301643_7.jpeg",
      "width": 3997,
      "height": 2250,
      "bgColor": ""
    },
    "language": "en"
  },
  {
    "titleText": "Invasive water weed threatens El Salvador wetland",
    "category": "Nature and Environment",
    "subCategory": null,
    "runningTime": 126,
    "updateTime": "2025-09-13T18:35:39.138Z",
    "onClick": {
      "targetAppId": "com.dw.app.dwforsmarttv",
      "contentId": "v=73982923&list=PROFILE_TOPIC_VIDEO:4",
      "type": "video",
      "id": 73982923,
      "launchParam": null
    },
    "providerLogo": {
      "url": "https://dwapps.de/feed/dw_white_800.png",
      "width": 800,
      "height": 800,
      "bgColor": ""
    },
    "image": {
      "url": "https://static.dw.com/image/73971468_6.jpg",
      "width": 940,
      "height": 529,
      "bgColor": ""
    },
    "image4k": {
      "url": "https://static.dw.com/image/73971468_7.jpg",
      "width": 3997,
      "height": 2250,
      "bgColor": ""
    },
    "language": "en"
  },
  {
    "titleText": "Why are so many Venezuelans fleeing to Europe?",
    "category": "Migration",
    "subCategory": null,
    "runningTime": 87,
    "updateTime": "2025-09-12T11:31:18.99Z",
    "onClick": {
      "targetAppId": "com.dw.app.dwforsmarttv",
      "contentId": "v=73975877&list=GLOBAL_TOPIC_VIDEO:3",
      "type": "video",
      "id": 73975877,
      "launchParam": null
    },
    "providerLogo": {
      "url": "https://dwapps.de/feed/dw_white_800.png",
      "width": 800,
      "height": 800,
      "bgColor": ""
    },
    "image": {
      "url": "https://static.dw.com/image/73975141_6.jpg",
      "width": 940,
      "height": 529,
      "bgColor": ""
    },
    "image4k": {
      "url": "https://static.dw.com/image/73975141_7.jpg",
      "width": 3997,
      "height": 2250,
      "bgColor": ""
    },
    "language": "en"
  },
  {
    "titleText": "Parasitic screwworm outbreak raises concerns in Texas",
    "category": "Nature and Environment",
    "subCategory": null,
    "runningTime": 145,
    "updateTime": "2025-08-15T19:52:24.682Z",
    "onClick": {
      "targetAppId": "com.dw.app.dwforsmarttv",
      "contentId": "v=73661878&list=GLOBAL_TOPIC_VIDEO:5",
      "type": "video",
      "id": 73661878,
      "launchParam": null
    },
    "providerLogo": {
      "url": "https://dwapps.de/feed/dw_white_800.png",
      "width": 800,
      "height": 800,
      "bgColor": ""
    },
    "image": {
      "url": "https://static.dw.com/image/64995943_6.jpg",
      "width": 940,
      "height": 529,
      "bgColor": ""
    },
    "image4k": {
      "url": "https://static.dw.com/image/64995943_7.jpg",
      "width": 3997,
      "height": 2250,
      "bgColor": ""
    },
    "language": "en"
  }
]